beancount_chase/__init__.py
LICENSE.txt
README.md
beancount_chase-1.0.0.dist-info/LICENSE.txt
beancount_chase-1.0.0.dist-info/WHEEL
beancount_chase-1.0.0.dist-info/METADATA
beancount_chase-1.0.0.dist-info/RECORD
