Metadata-Version: 2.1
Name: beancount-chase
Version: 1.0.0
Summary: Beancount Importer for Chase CSV statements
Home-page: https://github.com/ArthurFDLR/beancount-chase
License: MIT
Keywords: banking,beancount,cli-accounting,finance
Author: Arthur Findelair
Author-email: arthfind@gmail.com
Requires-Python: >=3.6,<4.0
Classifier: Development Status :: 5 - Production/Stable
Classifier: Environment :: Plugins
Classifier: Intended Audience :: End Users/Desktop
Classifier: Intended Audience :: Financial and Insurance Industry
Classifier: License :: OSI Approved :: MIT License
Classifier: Programming Language :: Python :: 3
Classifier: Programming Language :: Python :: 3 :: Only
Classifier: Programming Language :: Python :: 3.6
Classifier: Programming Language :: Python :: 3.7
Classifier: Programming Language :: Python :: 3.8
Classifier: Programming Language :: Python :: 3.9
Requires-Dist: beancount (>=2.3.3,<3.0.0)
Project-URL: Repository, https://github.com/ArthurFDLR/beancount-chase
